{
  "_class": "symbolInstance",
  "do_objectID": "DBE40B61-E1F5-4D62-A7F0-7373DD8708C7",
  "exportOptions": {
    "_class": "exportOptions",
    "exportFormats": [
    ],
    "includedLayerIds": [
    ],
    "layerOptions": 0,
    "shouldTrim": false
  },
  "frame": {
    "_class": "rect",
    "constrainProportions": false,
    "height": 15,
    "width": 20,
    "x": 0,
    "y": 2
  },
  "horizontalSpacing": 0,
  "isFlippedHorizontal": false,
  "isFlippedVertical": false,
  "isLocked": false,
  "isVisible": true,
  "layerListExpandedType": 0,
  "masterInfluenceEdgeMaxXPadding": 0,
  "masterInfluenceEdgeMaxYPadding": 0,
  "masterInfluenceEdgeMinXPadding": 0,
  "masterInfluenceEdgeMinYPadding": 0,
  "name": "icon / completed check",
  "nameIsFixed": false,
  "originalObjectID": "DBE40B61-E1F5-4D62-A7F0-7373DD8708C7",
  "overrides": {
  },
  "resizingConstraint": 63,
  "resizingType": 0,
  "rotation": 0,
  "shouldBreakMaskChain": false,
  "style": {
    "_class": "style",
    "endDecorationType": 0,
    "miterLimit": 10,
    "startDecorationType": 0
  },
  "symbolID": "C35ABE72-0EDE-42E8-B671-64A24EBA0428",
  "verticalSpacing": 0
}