{
  "_class": "group",
  "do_objectID": "BE5523D3-BD36-452D-B624-A6F7BCA47FD8",
  "exportOptions": {
    "_class": "exportOptions",
    "exportFormats": [
    ],
    "includedLayerIds": [
    ],
    "layerOptions": 0,
    "shouldTrim": false
  },
  "frame": {
    "_class": "rect",
    "constrainProportions": false,
    "height": 38,
    "width": 74,
    "x": 240,
    "y": 0
  },
  "hasClickThrough": false,
  "isFlippedHorizontal": false,
  "isFlippedVertical": false,
  "isLocked": false,
  "isVisible": true,
  "layerListExpandedType": 0,
  "layers": [
    {
      "class": "shapeGroup",
      "id": "9B59298E-3893-42C0-AD84-A580CA595A8F"
    },
    {
      "class": "text",
      "id": "22A7C912-5D8C-4D51-8B80-33A0D9BB35DE"
    }
  ],
  "name": "Return",
  "nameIsFixed": true,
  "resizingConstraint": 63,
  "resizingType": 0,
  "rotation": 0,
  "shouldBreakMaskChain": false,
  "style": {
    "_class": "style",
    "blur": {
      "_class": "blur",
      "center": "{0.5, 0.5}",
      "isEnabled": false,
      "motionAngle": 0,
      "radius": 5,
      "type": 0
    },
    "endDecorationType": 0,
    "fills": [
      {
        "_class": "fill",
        "color": {
          "_class": "color",
          "alpha": 0.1,
          "blue": 0,
          "green": 0,
          "red": 0
        },
        "fillType": 0,
        "isEnabled": true,
        "noiseIndex": 0,
        "noiseIntensity": 0,
        "patternFillType": 0,
        "patternTileScale": 1
      }
    ],
    "miterLimit": 10,
    "shadows": [
      {
        "_class": "shadow",
        "blurRadius": 0,
        "color": {
          "_class": "color",
          "alpha": 1,
          "blue": 0.5607843137254902,
          "green": 0.5450980392156862,
          "red": 0.5333333333333333
        },
        "contextSettings": {
          "_class": "graphicsContextSettings",
          "blendMode": 0,
          "opacity": 1
        },
        "isEnabled": false,
        "offsetX": 0,
        "offsetY": 1,
        "spread": 0
      }
    ],
    "startDecorationType": 0
  }
}