{
  "_class": "symbolInstance",
  "do_objectID": "C92F9E8C-29BD-4EE4-B053-7DDFF4C26558",
  "exportOptions": {
    "_class": "exportOptions",
    "exportFormats": [
    ],
    "includedLayerIds": [
    ],
    "layerOptions": 0,
    "shouldTrim": false
  },
  "frame": {
    "_class": "rect",
    "constrainProportions": false,
    "height": 19,
    "width": 107,
    "x": 14,
    "y": 13
  },
  "horizontalSpacing": 0,
  "isFlippedHorizontal": false,
  "isFlippedVertical": false,
  "isLocked": false,
  "isVisible": true,
  "layerListExpandedType": 0,
  "masterInfluenceEdgeMaxXPadding": 0,
  "masterInfluenceEdgeMaxYPadding": 0,
  "masterInfluenceEdgeMinXPadding": 0,
  "masterInfluenceEdgeMinYPadding": 0,
  "name": "Type / Open Sans / 14 / Reg / Blue / Center",
  "nameIsFixed": false,
  "overrides": {
  },
  "resizingConstraint": 63,
  "resizingType": 0,
  "rotation": 0,
  "shouldBreakMaskChain": false,
  "style": {
    "_class": "style",
    "endDecorationType": 0,
    "miterLimit": 10,
    "startDecorationType": 0
  },
  "symbolID": "3E106994-ABC8-4684-A1DF-C069B9724BEE",
  "verticalSpacing": 0
}