{
  "_class": "shapePath",
  "booleanOperation": -1,
  "do_objectID": "A2084716-9F71-4892-B21D-95015549413D",
  "edited": true,
  "exportOptions": {
    "_class": "exportOptions",
    "exportFormats": [
    ],
    "includedLayerIds": [
    ],
    "layerOptions": 0,
    "shouldTrim": false
  },
  "frame": {
    "_class": "rect",
    "constrainProportions": false,
    "height": 16.63321799307959,
    "width": 16.62705984388552,
    "x": 1.186470078057242,
    "y": 1.183391003460206
  },
  "isFlippedHorizontal": false,
  "isFlippedVertical": false,
  "isLocked": false,
  "isVisible": true,
  "layerListExpandedType": 0,
  "name": "Path",
  "nameIsFixed": false,
  "path": {
    "_class": "path",
    "isClosed": true,
    "pointRadiusBehaviour": 0,
    "points": [
      {
        "_class": "curvePoint",
        "cornerRadius": 0,
        "curveFrom": "{0.22398414271556003, 1}",
        "curveMode": 2,
        "curveTo": "{0.77601585728444022, 1}",
        "hasCurveFrom": true,
        "hasCurveTo": true,
        "point": "{0.49950445986124886, 1}"
      },
      {
        "_class": "curvePoint",
        "cornerRadius": 0,
        "curveFrom": "{0, 0.22430830039525704}",
        "curveMode": 2,
        "curveTo": "{0, 0.77569169960474316}",
        "hasCurveFrom": true,
        "hasCurveTo": true,
        "point": "{0, 0.50000000000000011}"
      },
      {
        "_class": "curvePoint",
        "cornerRadius": 0,
        "curveFrom": "{0.77601585728444022, 0}",
        "curveMode": 2,
        "curveTo": "{0.22398414271556003, 0}",
        "hasCurveFrom": true,
        "hasCurveTo": true,
        "point": "{0.49950445986124886, 0}"
      },
      {
        "_class": "curvePoint",
        "cornerRadius": 0,
        "curveFrom": "{1, 0.77569169960474316}",
        "curveMode": 2,
        "curveTo": "{1, 0.22430830039525704}",
        "hasCurveFrom": true,
        "hasCurveTo": true,
        "point": "{1, 0.50000000000000011}"
      }
    ]
  },
  "resizingConstraint": 63,
  "resizingType": 0,
  "rotation": 0,
  "shouldBreakMaskChain": false
}