{
  "_class": "shapeGroup",
  "clippingMaskMode": 0,
  "do_objectID": "705297AA-FF1E-4DF4-B3E0-A6D768636892",
  "exportOptions": {
    "_class": "exportOptions",
    "exportFormats": [
    ],
    "includedLayerIds": [
    ],
    "layerOptions": 0,
    "shouldTrim": false
  },
  "frame": {
    "_class": "rect",
    "constrainProportions": false,
    "height": 318,
    "width": 320,
    "x": 0,
    "y": 0
  },
  "hasClickThrough": false,
  "hasClippingMask": false,
  "isFlippedHorizontal": false,
  "isFlippedVertical": false,
  "isLocked": false,
  "isVisible": true,
  "layerListExpandedType": 0,
  "layers": [
    {
      "class": "rectangle",
      "id": "C9CDD4D8-4758-4BC8-8E84-F17ECF1D1F0C"
    }
  ],
  "name": "BG",
  "nameIsFixed": true,
  "resizingConstraint": 63,
  "resizingType": 0,
  "rotation": 0,
  "shouldBreakMaskChain": false,
  "style": {
    "sharedObjectID": "EBEC90B4-D310-45EE-A600-294B9DCD9CFF"
  },
  "windingRule": 1
}