{
  "_class": "group",
  "do_objectID": "DC0D052B-1608-43DB-8E03-4D8D682CE320",
  "exportOptions": {
    "_class": "exportOptions",
    "exportFormats": [
    ],
    "includedLayerIds": [
    ],
    "layerOptions": 0,
    "shouldTrim": false
  },
  "frame": {
    "_class": "rect",
    "constrainProportions": false,
    "height": 12,
    "width": 7,
    "x": 9,
    "y": 6
  },
  "hasClickThrough": false,
  "isFlippedHorizontal": false,
  "isFlippedVertical": false,
  "isLocked": false,
  "isVisible": true,
  "layerListExpandedType": 0,
  "layers": [
    {
      "class": "shapeGroup",
      "id": "7046288A-6C3C-4093-A442-B29684721124"
    },
    {
      "class": "symbolInstance",
      "id": "6B17158A-CF4D-4B70-BE3A-7276EE925FB8"
    }
  ],
  "name": "Elements / Color / Black",
  "nameIsFixed": false,
  "originalObjectID": "DC0D052B-1608-43DB-8E03-4D8D682CE320",
  "resizingConstraint": 63,
  "resizingType": 0,
  "rotation": -90,
  "shouldBreakMaskChain": false,
  "style": {
    "_class": "style",
    "endDecorationType": 0,
    "miterLimit": 10,
    "startDecorationType": 0
  }
}