{
  "_class": "group",
  "do_objectID": "C7175E95-59AB-45B7-A9F5-E79047DB5524",
  "exportOptions": {
    "_class": "exportOptions",
    "exportFormats": [
    ],
    "includedLayerIds": [
    ],
    "layerOptions": 0,
    "shouldTrim": false
  },
  "frame": {
    "_class": "rect",
    "constrainProportions": false,
    "height": 503,
    "width": 363,
    "x": 203,
    "y": 0
  },
  "hasClickThrough": false,
  "isFlippedHorizontal": false,
  "isFlippedVertical": false,
  "isLocked": false,
  "isVisible": true,
  "layerListExpandedType": 0,
  "layers": [
    {
      "class": "shapeGroup",
      "id": "EAE1AFDC-2A52-4C35-9C58-29AF0502AA8A"
    },
    {
      "class": "text",
      "id": "9444CD7C-C780-4546-8F8C-BF1C3DA3C57B"
    },
    {
      "class": "group",
      "id": "ED9C01CC-857E-4AAA-8554-3E082269F2B9"
    },
    {
      "class": "text",
      "id": "0719E556-C032-4525-A82F-5B1A16A08683"
    },
    {
      "class": "group",
      "id": "C68033F1-01CC-419D-BA68-BE640D1835EE"
    },
    {
      "class": "text",
      "id": "88D4372D-60C1-4365-A441-80F82A51902E"
    },
    {
      "class": "text",
      "id": "102318C4-D669-400D-84A2-85A768AA0761"
    }
  ],
  "name": "Group",
  "nameIsFixed": false,
  "resizingConstraint": 63,
  "resizingType": 0,
  "rotation": 0,
  "shouldBreakMaskChain": false,
  "style": {
    "_class": "style",
    "endDecorationType": 0,
    "miterLimit": 10,
    "startDecorationType": 0
  }
}