{
  "_class": "symbolInstance",
  "do_objectID": "6D46FAF3-681D-4FC8-90B2-A60DA9466E44",
  "exportOptions": {
    "_class": "exportOptions",
    "exportFormats": [
    ],
    "includedLayerIds": [
    ],
    "layerOptions": 0,
    "shouldTrim": false
  },
  "frame": {
    "_class": "rect",
    "constrainProportions": false,
    "height": 24,
    "width": 24,
    "x": 16,
    "y": 40
  },
  "horizontalSpacing": 0,
  "isFlippedHorizontal": false,
  "isFlippedVertical": false,
  "isLocked": false,
  "isVisible": true,
  "layerListExpandedType": 0,
  "masterInfluenceEdgeMaxXPadding": 0,
  "masterInfluenceEdgeMaxYPadding": 0,
  "masterInfluenceEdgeMinXPadding": 0,
  "masterInfluenceEdgeMinYPadding": 0,
  "name": "Back",
  "nameIsFixed": true,
  "originalObjectID": "8102DFB9-18FD-442B-8071-4E905AF3682C",
  "overrides": {
    "25C86601-C23D-454E-A603-88365BB94B55": {
      "symbolID": "E5B808A3-F893-4EBB-9790-138534C3998B"
    }
  },
  "resizingConstraint": 63,
  "resizingType": 0,
  "rotation": 0,
  "shouldBreakMaskChain": false,
  "style": {
    "_class": "style",
    "endDecorationType": 0,
    "miterLimit": 10,
    "startDecorationType": 0
  },
  "symbolID": "16399D1C-A2F4-46A2-9734-BB85AB69674E",
  "verticalSpacing": 0
}