{
  "_class": "group",
  "do_objectID": "758C233E-F85F-4243-970C-89E96A1C71DC",
  "exportOptions": {
    "_class": "exportOptions",
    "exportFormats": [
    ],
    "includedLayerIds": [
    ],
    "layerOptions": 0,
    "shouldTrim": false
  },
  "frame": {
    "_class": "rect",
    "constrainProportions": false,
    "height": 128,
    "width": 672,
    "x": 688,
    "y": 638
  },
  "hasClickThrough": false,
  "isFlippedHorizontal": false,
  "isFlippedVertical": false,
  "isLocked": false,
  "isVisible": true,
  "layerListExpandedType": 0,
  "layers": [
    {
      "class": "symbolInstance",
      "id": "227B6D0E-38CE-49C9-B486-EB912FEB7447"
    },
    {
      "class": "text",
      "id": "48A8763B-A478-449F-A083-20C7DB5D0237"
    }
  ],
  "name": "iPad Body L3",
  "nameIsFixed": true,
  "resizingConstraint": 63,
  "resizingType": 0,
  "rotation": 0,
  "shouldBreakMaskChain": false,
  "style": {
    "_class": "style",
    "endDecorationType": 0,
    "miterLimit": 10,
    "startDecorationType": 0
  }
}