{
  "_class": "group",
  "do_objectID": "6CB937A6-78B9-4920-9DF5-C99C76DAE47D",
  "exportOptions": {
    "_class": "exportOptions",
    "exportFormats": [
    ],
    "includedLayerIds": [
    ],
    "layerOptions": 0,
    "shouldTrim": false
  },
  "frame": {
    "_class": "rect",
    "constrainProportions": false,
    "height": 44,
    "width": 170,
    "x": 0,
    "y": 0
  },
  "hasClickThrough": false,
  "isFlippedHorizontal": false,
  "isFlippedVertical": false,
  "isLocked": false,
  "isVisible": true,
  "layerListExpandedType": 2,
  "layers": [
    {
      "class": "shapeGroup",
      "id": "2ED9F689-D1F6-4B6B-B546-F8D79F272965"
    },
    {
      "class": "text",
      "id": "FD8C411A-D91E-4595-91FD-EEAD3B7F9FF9"
    },
    {
      "class": "text",
      "id": "1240FC3E-CB83-4EAA-B33B-ED94EDEC9B5A"
    }
  ],
  "name": "Time Zone",
  "nameIsFixed": true,
  "originalObjectID": "6CB937A6-78B9-4920-9DF5-C99C76DAE47D",
  "resizingConstraint": 63,
  "resizingType": 0,
  "rotation": 0,
  "shouldBreakMaskChain": false,
  "style": {
    "_class": "style",
    "endDecorationType": 0,
    "miterLimit": 10,
    "startDecorationType": 0
  }
}